.gitignore
MANIFEST.in
README.rst
bootstrap.py
buildout.cfg
setup.py
collective/__init__.py
collective.js.ckeditor.egg-info/PKG-INFO
collective.js.ckeditor.egg-info/SOURCES.txt
collective.js.ckeditor.egg-info/dependency_links.txt
collective.js.ckeditor.egg-info/entry_points.txt
collective.js.ckeditor.egg-info/namespace_packages.txt
collective.js.ckeditor.egg-info/not-zip-safe
collective.js.ckeditor.egg-info/requires.txt
collective.js.ckeditor.egg-info/top_level.txt
collective/js/__init__.py
collective/js/ckeditor/__init__.py
collective/js/ckeditor/configure.zcml
collective/js/ckeditor/interfaces.py
collective/js/ckeditor/testing.py
collective/js/ckeditor/upgrades.py
collective/js/ckeditor/upgrades.zcml
collective/js/ckeditor/profiles/default/jsregistry.xml
collective/js/ckeditor/profiles/default/metadata.xml
collective/js/ckeditor/resources/ckeditor.js
collective/js/ckeditor/resources/config.js
collective/js/ckeditor/resources/contents.css
collective/js/ckeditor/resources/plone.js
collective/js/ckeditor/resources/styles.js
collective/js/ckeditor/resources/lang/af.js
collective/js/ckeditor/resources/lang/ar.js
collective/js/ckeditor/resources/lang/bg.js
collective/js/ckeditor/resources/lang/bn.js
collective/js/ckeditor/resources/lang/bs.js
collective/js/ckeditor/resources/lang/ca.js
collective/js/ckeditor/resources/lang/cs.js
collective/js/ckeditor/resources/lang/cy.js
collective/js/ckeditor/resources/lang/da.js
collective/js/ckeditor/resources/lang/de.js
collective/js/ckeditor/resources/lang/el.js
collective/js/ckeditor/resources/lang/en-au.js
collective/js/ckeditor/resources/lang/en-ca.js
collective/js/ckeditor/resources/lang/en-gb.js
collective/js/ckeditor/resources/lang/en.js
collective/js/ckeditor/resources/lang/eo.js
collective/js/ckeditor/resources/lang/es.js
collective/js/ckeditor/resources/lang/et.js
collective/js/ckeditor/resources/lang/eu.js
collective/js/ckeditor/resources/lang/fa.js
collective/js/ckeditor/resources/lang/fi.js
collective/js/ckeditor/resources/lang/fo.js
collective/js/ckeditor/resources/lang/fr-ca.js
collective/js/ckeditor/resources/lang/fr.js
collective/js/ckeditor/resources/lang/gl.js
collective/js/ckeditor/resources/lang/gu.js
collective/js/ckeditor/resources/lang/he.js
collective/js/ckeditor/resources/lang/hi.js
collective/js/ckeditor/resources/lang/hr.js
collective/js/ckeditor/resources/lang/hu.js
