Metadata-Version: 1.0
Name: collective.js.ckeditor
Version: 4.0.3
Summary: Just register ckeditor resources to Plone registry
Home-page: https://github.com/toutpt/collective.js.ckeditor
Author: JeanMichel FRANCOIS
Author-email: toutpt@gmail.com
License: GPL
Keywords: plone ckeditor
Platform: UNKNOWN
Classifier: Environment :: Web Environment
Classifier: License :: OSI Approved :: GNU General Public License (GPL)
Classifier: Operating System :: OS Independent
Classifier: Framework :: Zope2
Classifier: Framework :: Plone
Classifier: Framework :: Plone :: 4.0
Classifier: Framework :: Plone :: 4.1
Classifier: Framework :: Plone :: 4.2
Classifier: Framework :: Plone :: 4.3
Classifier: Programming Language :: Python
Classifier: Programming Language :: Python :: 2.6
Classifier: Programming Language :: Python :: 2.7
